[
  {
    "id": 1,
    "name": "Roni Patoroni",
    "position": "Director",
    "company": "Ardan Mindworks",
    "email": "",
    "phone": "",
    "bio": "Director of Ardan Mindworks",
    "image": "/logo-perusahaan/SPT_2024_Ardan Mindworks.jpg",
    "bgColor": "bg-amber-900"
  },
  {
    "id": 2,
    "name": "Yeni Wahyuningsih",
    "position": "Director",
    "company": "Lima",
    "email": "",
    "phone": "",
    "bio": "Director of Lima",
    "image": "/logo-perusahaan/Logo_Rich Music (W).PNG",
    "bgColor": "bg-slate-800"
  },
  {
    "id": 3,
    "name": "Herlan Susila",
    "position": "Director",
    "company": "NBA",
    "email": "",
    "phone": "",
    "bio": "Director of NBA",
    "image": "/logo-perusahaan/logo nba white@330x.png",
    "bgColor": "bg-black"
  },
  {
    "id": 4,
    "name": "Herviana Suminar",
    "position": "Director",
    "company": "NICE",
    "email": "",
    "phone": "",
    "bio": "Director of NICE",
    "image": "/logo-perusahaan/Nice.jpg",
    "bgColor": "bg-white"
  },
  {
    "id": 5,
    "name": "Reky Hermawan",
    "position": "Director",
    "company": "Redbox",
    "email": "",
    "phone": "",
    "bio": "Director of Redbox",
    "image": "/logo-perusahaan/REDBOX.jpg",
    "bgColor": "bg-black"
  },
  {
    "id": 6,
    "name": "Inyo Tanius Saleh",
    "position": "Director",
    "company": "Rumah Event Indonesia",
    "email": "",
    "phone": "",
    "bio": "Director of Rumah Event Indonesia",
    "image": "/logo-perusahaan/WhatsApp Image 2025-02-14 at 09.31.54_c1e0cc83.jpg",
    "bgColor": "bg-white"
  },
  {
    "id": 7,
    "name": "Mursito",
    "position": "Director",
    "company": "Siqlus",
    "email": "",
    "phone": "",
    "bio": "Director of Siqlus",
    "image": "/logo-perusahaan/Siqlus.jpg",
    "bgColor": "bg-white"
  },
  {
    "id": 8,
    "name": "Roni Nur MS",
    "position": "Director",
    "company": "CV Satria Prima Perkasa",
    "email": "",
    "phone": "",
    "bio": "Director of CV Satria Prima Perkasa",
    "image": "/logo-perusahaan/LOGO_SPP_CORP.png",
    "bgColor": "bg-white"
  },
  {
    "id": 9,
    "name": "Endang Hidayat",
    "position": "Director",
    "company": "CV Kukami Indonesia",
    "email": "",
    "phone": "",
    "bio": "Director of CV Kukami Indonesia",
    "image": "/logo-perusahaan/Kukami.jpg",
    "bgColor": "bg-yellow-900"
  },
  {
    "id": 10,
    "name": "Rullyana Kamaludin",
    "position": "Director",
    "company": "Eleven B Entertainment",
    "email": "",
    "phone": "",
    "bio": "Director of Eleven B Entertainment",
    "image": "/logo-perusahaan/Logo_Rich Music (B).PNG",
    "bgColor": "bg-white"
  },
  {
    "id": 11,
    "name": "Bayu Subekti",
    "position": "Director",
    "company": "PT Tiga Pesona Teknologi",
    "email": "",
    "phone": "",
    "bio": "Director of PT Tiga Pesona Teknologi",
    "image": "/logo-perusahaan/Tiga_Pesona_Teknologi.jpg",
    "bgColor": "bg-white"
  },
  {
    "id": 12,
    "name": "Yosep Sobandi",
    "position": "Director",
    "company": "Dealpro",
    "email": "",
    "phone": "",
    "bio": "Director of Dealpro",
    "image": "/logo-perusahaan/LOGO_DEALPRO.jpg",
    "bgColor": "bg-white"
  },
  {
    "id": 13,
    "name": "Yusup Saepulloh",
    "position": "Director",
    "company": "Trisi Project",
    "email": "",
    "phone": "",
    "bio": "Director of Trisi Project",
    "image": "/logo-perusahaan/Logo_Trisi_Project.pdf",
    "bgColor": "bg-rose-900"
  },
  {
    "id": 14,
    "name": "Ariyo Sulistijo",
    "position": "Director",
    "company": "KAT",
    "email": "",
    "phone": "",
    "bio": "Director of KAT",
    "image": "/logo-perusahaan/KAT.png",
    "bgColor": "bg-orange-900"
  },
  {
    "id": 15,
    "name": "Budi Darmawan",
    "position": "Director",
    "company": "Masagi",
    "email": "",
    "phone": "",
    "bio": "Director of Masagi",
    "image": "/logo-perusahaan/Masagi.jpg",
    "bgColor": "bg-white"
  },
  {
    "id": 16,
    "name": "Hary HB Sunarko",
    "position": "Director",
    "company": "Gandrung Events",
    "email": "",
    "phone": "",
    "bio": "Director of Gandrung Events",
    "image": "/logo-perusahaan/Gandrung.jpg",
    "bgColor": "bg-white"
  },
  {
    "id": 17,
    "name": "Giovitano",
    "position": "Director",
    "company": "Atap Promotions",
    "email": "",
    "phone": "",
    "bio": "Director of Atap Promotions",
    "image": "/logo-perusahaan/ATAP PROMOTIONS LOGO HORIZONTAL - WHITE RED-01 2.png",
    "bgColor": "bg-red-800"
  },
  {
    "id": 18,
    "name": "Andri Akmarsyah",
    "position": "Director",
    "company": "Jiva Events",
    "email": "",
    "phone": "",
    "bio": "Director of Jiva Events",
    "image": "/logo-perusahaan/Jiva Event .jpg",
    "bgColor": "bg-black"
  },
  {
    "id": 19,
    "name": "Indra Nugraha S Sos",
    "position": "Director",
    "company": "CV. Laatansa Cahaya Anugrah",
    "email": "",
    "phone": "",
    "bio": "Director of CV. Laatansa Cahaya Anugrah",
    "image": "data:image/svg+xml,%3Csvg xmlns='http://www.w3.org/2000/svg' width='200' height='100'%3E%3Crect fill='%23666' width='200' height='100'/%3E%3Ctext x='50%25' y='50%25' font-size='12' fill='%23fff' text-anchor='middle' dominant-baseline='middle' font-family='Arial'%3ECV. Laatansa Cahaya Anugrah%3C/text%3E%3C/svg%3E",
    "bgColor": "bg-gray-700"
  },
  {
    "id": 20,
    "name": "Icha Donchu",
    "position": "Director",
    "company": "PT Mega Adreena Jaya",
    "email": "",
    "phone": "",
    "bio": "Director of PT Mega Adreena Jaya",
    "image": "/logo-perusahaan/LOGO MINDWORKS 2017 B.png",
    "bgColor": "bg-amber-900"
  },
  {
    "id": 21,
    "name": "Inge",
    "position": "Director",
    "company": "PT. AVAS (INKRI, Religion Even5 management)",
    "email": "",
    "phone": "",
    "bio": "Director of PT. AVAS (INKRI, Religion Even5 management)",
    "image": "/logo-perusahaan/LOGO MINDWORKS 2017 W.png",
    "bgColor": "bg-slate-700"
  },
  {
    "id": 22,
    "name": "Riksa Bakti Andayaguna",
    "position": "Director",
    "company": "D'Partners (PT Ramayana Bahana Antariksa)",
    "email": "",
    "phone": "",
    "bio": "Director of D'Partners (PT Ramayana Bahana Antariksa)",
    "image": "/logo-perusahaan/DPARTNERS_LOGO_BLACK_V.png",
    "bgColor": "bg-white"
  },
  {
    "id": 23,
    "name": "Mochamad Andika",
    "position": "Director",
    "company": "PT Langit Sumber Media",
    "email": "",
    "phone": "",
    "bio": "Director of PT Langit Sumber Media",
    "image": "data:image/svg+xml,%3Csvg xmlns='http://www.w3.org/2000/svg' width='200' height='100'%3E%3Crect fill='%23666' width='200' height='100'/%3E%3Ctext x='50%25' y='50%25' font-size='14' fill='%23fff' text-anchor='middle' dominant-baseline='middle' font-family='Arial'%3EPT Langit Sumber Media%3C/text%3E%3C/svg%3E",
    "bgColor": "bg-gray-700"
  },
  {
    "id": 24,
    "name": "Ratih Cinthia Dewi",
    "position": "Director",
    "company": "PT Astadeca Baswara Persada",
    "email": "",
    "phone": "",
    "bio": "Director of PT Astadeca Baswara Persada",
    "image": "/logo-perusahaan/Kukami.jpg",
    "bgColor": "bg-yellow-900"
  },
  {
    "id": 25,
    "name": "Guriang",
    "position": "Director",
    "company": "Tiga Bintang",
    "email": "",
    "phone": "",
    "bio": "Director of Tiga Bintang",
    "image": "data:image/svg+xml,%3Csvg xmlns='http://www.w3.org/2000/svg' width='200' height='100'%3E%3Crect fill='%23666' width='200' height='100'/%3E%3Ctext x='50%25' y='50%25' font-size='16' fill='%23fff' text-anchor='middle' dominant-baseline='middle' font-family='Arial'%3ETiga Bintang%3C/text%3E%3C/svg%3E",
    "bgColor": "bg-gray-700"
  },
  {
    "id": 26,
    "name": "Ricky",
    "position": "Director",
    "company": "Sauyunan",
    "email": "",
    "phone": "",
    "bio": "Director of Sauyunan",
    "image": "data:image/svg+xml,%3Csvg xmlns='http://www.w3.org/2000/svg' width='200' height='100'%3E%3Crect fill='%23666' width='200' height='100'/%3E%3Ctext x='50%25' y='50%25' font-size='18' fill='%23fff' text-anchor='middle' dominant-baseline='middle' font-family='Arial'%3ESauyunan%3C/text%3E%3C/svg%3E",
    "bgColor": "bg-gray-700"
  }
]